degurba/__init__.py
degurba/io.py
degurba/load_data.py
degurba/main.py
degurba/utils.py
degurba-0.1.dist-info/METADATA
degurba-0.1.dist-info/WHEEL
degurba-0.1.dist-info/top_level.txt
degurba-0.1.dist-info/RECORD
