Metadata-Version: 2.2
Name: degurba
Version: 0.1
Summary: Urban Boundary Extraction Software Based on Degree of Urbanization
Home-page: https://github.com/djw-easy/degurba
Author: Your Name
Author-email: djw@lreis.ac.cn
Classifier: Programming Language :: Python :: 3
Classifier: License :: OSI Approved :: MIT License
Classifier: Operating System :: OS Independent
Requires-Python: >=3.7
Requires-Dist: rasterio
Requires-Dist: scipy
Dynamic: author
Dynamic: author-email
Dynamic: classifier
Dynamic: description
Dynamic: description-content-type
Dynamic: home-page
Dynamic: requires-dist
Dynamic: requires-python
Dynamic: summary
